aliyunsdkcciotgw/__init__.py
aliyunsdkcciotgw/request/__init__.py
aliyunsdkcciotgw/request/v20210721/AddCloudConnectorGatewayPrivilegeRequest.py
aliyunsdkcciotgw/request/v20210721/AddIpToConnectionPoolFromExcelRequest.py
aliyunsdkcciotgw/request/v20210721/AllocateIpsRequest.py
aliyunsdkcciotgw/request/v20210721/AssociateIccidToIpExcelRequest.py
aliyunsdkcciotgw/request/v20210721/AssociateIccidToIpRequest.py
aliyunsdkcciotgw/request/v20210721/DeleteCloudConnectorGatewayPrivilegeRequest.py
aliyunsdkcciotgw/request/v20210721/GetFreeIpCountRequest.py
aliyunsdkcciotgw/request/v20210721/GetIccidAndIpRequest.py
aliyunsdkcciotgw/request/v20210721/GetIoTCloudConnectorGatewayRequest.py
aliyunsdkcciotgw/request/v20210721/GetIpStatusRequest.py
aliyunsdkcciotgw/request/v20210721/ListCloudConnectorGatewayPrivilegeRequest.py
aliyunsdkcciotgw/request/v20210721/ListConnectionPoolIpRequest.py
aliyunsdkcciotgw/request/v20210721/ListGreInterfacesRequest.py
aliyunsdkcciotgw/request/v20210721/ListIoTCloudConnectorGatewaysRequest.py
aliyunsdkcciotgw/request/v20210721/ListIpsStatusRequest.py
aliyunsdkcciotgw/request/v20210721/ListResultTokenUrlRequest.py
aliyunsdkcciotgw/request/v20210721/ModifyIpStatusRequest.py
aliyunsdkcciotgw/request/v20210721/QueryAsynTokenResultRequest.py
aliyunsdkcciotgw/request/v20210721/SwitchVpcRouteToBackUpZoneRequest.py
aliyunsdkcciotgw/request/v20210721/UnAssociateIccidToIpRequest.py
aliyunsdkcciotgw/request/v20210721/__init__.py
aliyun_python_sdk_cciotgw-1.0.1.dist-info/LICENSE
aliyun_python_sdk_cciotgw-1.0.1.dist-info/METADATA
aliyun_python_sdk_cciotgw-1.0.1.dist-info/WHEEL
aliyun_python_sdk_cciotgw-1.0.1.dist-info/top_level.txt
aliyun_python_sdk_cciotgw-1.0.1.dist-info/RECORD
